[{"type":"sprite","x":0,"y":0,"name":"","0":{"x":389.55,"y":868.8,"name":"break1","type":"sprite","r":0,"sx":1,"sy":1,"a":1,"skewX":0,"skewY":0,"0":{"x":0,"y":38.4,"name":"tower","type":"sprite","r":0,"sx":1,"sy":1,"a":0,"skewX":0,"skewY":0,"0":{"type":"bitmap","libName":"towels_surround.png","x":0,"y":0,"r":0,"sx":1,"sy":1,"skewX":0,"skewY":0}},"1":{"x":44.25,"y":128.5,"name":"area","type":"sprite","r":0,"sx":3.940765380859375,"sy":2.7726898193359375,"a":1,"skewX":0,"skewY":0,"0":{"type":"bitmap","libName":"Bitmap 5","x":0,"y":0,"r":0,"sx":1,"sy":1.0000457763671875,"skewX":0,"skewY":0}},"2":{"type":"bitmap","libName":"ices_breaker.png","x":0,"y":0,"r":0,"sx":1,"sy":1,"skewX":0,"skewY":0}},"1":{"x":268.1,"y":609.15,"name":"tower","type":"sprite","r":0,"sx":1,"sy":1,"a":1,"skewX":0,"skewY":0,"0":{"type":"bitmap","libName":"towels.png","x":0,"y":0,"r":0,"sx":1.3763275146484375,"sy":1.3763275146484375,"skewX":0,"skewY":0}},"2":{"x":975.2,"y":793.55,"name":"ther","type":"sprite","r":0,"sx":1,"sy":1,"a":1,"skewX":0,"skewY":0,"0":{"x":-24.5,"y":252.35,"name":"ice","type":"sprite","r":0,"sx":0.91302490234375,"sy":0.8636322021484375,"a":0,"skewX":0,"skewY":0,"0":{"type":"bitmap","libName":"ice.png","x":0,"y":0,"r":0,"sx":1,"sy":1,"skewX":0,"skewY":0}},"1":{"x":223.6,"y":39.5,"name":"big","type":"sprite","r":0,"sx":1,"sy":1,"a":1,"skewX":0,"skewY":0,"0":{"x":0,"y":-2.7,"name":"waterColumn","type":"sprite","r":0,"sx":1,"sy":1,"a":1,"skewX":0,"skewY":0,"0":{"type":"bitmap","libName":"Bitmap 11.png","x":-6.25,"y":0,"r":0,"sx":2.50799560546875,"sy":18.179122924804688,"skewX":0,"skewY":0}},"1":{"x":-0.05,"y":0,"name":"bigTemp","type":"sprite","r":0,"sx":1,"sy":1,"a":1,"skewX":0,"skewY":0,"0":{"type":"bitmap","libName":"thermometer_big1.png","x":-65,"y":-1188.25,"r":0,"sx":1,"sy":1,"skewX":0,"skewY":0}},"2":{"x":4,"y":74.55,"name":"zoom","type":"sprite","r":0,"sx":1,"sy":1,"a":1,"skewX":0,"skewY":0,"0":{"x":0,"y":-89.5,"name":"eye","type":"sprite","r":0,"sx":1,"sy":1,"a":1,"skewX":0,"skewY":0,"0":{"type":"bitmap","libName":"Bitmap 8","x":0,"y":0,"r":0,"sx":1,"sy":1,"skewX":0,"skewY":0},"1":{"type":"bitmap","libName":"Bitmap 6","x":360.25,"y":-13.45,"r":0,"sx":1,"sy":1,"skewX":0,"skewY":0},"2":{"x":223.3,"y":-25.7,"w":188,"h":65.4,"name":"txt","type":"text","r":0,"txt":"n","a":"center","f":"45px '微软雅黑'","c":"#FFFFFF"}},"1":{"type":"bitmap","libName":"magnifier glass.png","x":-177.5,"y":-154.5,"r":0,"sx":1,"sy":1,"skewX":0,"skewY":0}}},"2":{"type":"bitmap","libName":"Bitmap 10.png","x":4.8,"y":395.95,"r":0,"sx":1,"sy":0.0293121337890625,"skewX":0,"skewY":0},"3":{"x":4.8,"y":396.4,"name":"waterColumn","type":"sprite","r":0,"sx":1,"sy":1,"a":1,"skewX":0,"skewY":0,"0":{"type":"bitmap","libName":"Bitmap 10.png","x":0,"y":-342,"r":0,"sx":1,"sy":1,"skewX":0,"skewY":0}},"4":{"x":-21.55,"y":365.45,"name":"bottom","type":"sprite","r":0,"sx":0.788330078125,"sy":0.973663330078125,"a":1,"skewX":0,"skewY":0,"0":{"type":"bitmap","libName":"Bitmap 5","x":0,"y":0,"r":0,"sx":1,"sy":1.0000457763671875,"skewX":0,"skewY":0}},"5":{"x":0,"y":407.55,"name":"head","type":"sprite","r":0,"sx":0.2144012451171875,"sy":0.3536376953125,"a":1,"skewX":0,"skewY":0,"0":{"type":"bitmap","libName":"Bitmap 5","x":0,"y":0,"r":0,"sx":1,"sy":1.0000457763671875,"skewX":0,"skewY":0}},"6":{"x":-35.1,"y":75.85,"name":"","type":"sprite","r":0,"sx":1,"sy":1,"a":1,"skewX":0,"skewY":0,"0":{"x":-27.9,"y":-22.5,"name":"area","type":"sprite","r":0,"sx":1.94122314453125,"sy":4.92242431640625,"a":1,"skewX":0,"skewY":0,"0":{"type":"bitmap","libName":"Bitmap 5","x":0,"y":0,"r":0,"sx":1,"sy":1.0000457763671875,"skewX":0,"skewY":0}},"1":{"type":"bitmap","libName":"Bitmap 4","x":5.3,"y":76.95,"r":0,"sx":1.04705810546875,"sy":1.04705810546875,"skewX":0,"skewY":0},"2":{"x":5.9,"y":79.3,"name":"shiguan","type":"sprite","r":0,"sx":1,"sy":1,"a":1,"skewX":0,"skewY":0,"0":{"type":"bitmap","libName":"Bitmap 3","x":0,"y":0,"r":0,"sx":1,"sy":1,"skewX":0,"skewY":0}},"3":{"x":10,"y":174.6,"name":"","type":"sprite","r":0,"sx":0.9071044921875,"sy":0.866241455078125,"a":0,"skewX":0,"skewY":0,"0":{"type":"bitmap","libName":"ice.png","x":0,"y":0,"r":0,"sx":1,"sy":1,"skewX":0,"skewY":0}}},"7":{"x":-48.05,"y":0,"name":"moveArea","type":"sprite","r":0,"sx":1.65667724609375,"sy":5.3107147216796875,"a":1,"skewX":0,"skewY":0,"0":{"type":"bitmap","libName":"Bitmap 5","x":0,"y":0,"r":0,"sx":1,"sy":1.0000457763671875,"skewX":0,"skewY":0}},"8":{"type":"bitmap","libName":"thermometer_up.png","x":0,"y":0,"r":0,"sx":1,"sy":1,"skewX":0,"skewY":0}}},{"type":"sprite","x":0,"y":0,"name":"frame2","0":{"x":206.35,"y":597.1,"name":"spoonHitRef","type":"sprite","r":0,"sx":3.744842529296875,"sy":3.66717529296875,"a":1,"skewX":0,"skewY":0,"0":{"type":"bitmap","libName":"Bitmap 5","x":0,"y":0,"r":0,"sx":1,"sy":1.0000457763671875,"skewX":0,"skewY":0}},"1":{"x":686.8,"y":1226.25,"name":"shiguan","type":"sprite","r":0,"sx":1,"sy":1,"a":1,"skewX":0,"skewY":0,"0":{"type":"bitmap","libName":"Bitmap 20","x":0,"y":0,"r":0,"sx":1,"sy":1,"skewX":0,"skewY":0}},"2":{"type":"bitmap","libName":"Bitmap 19","x":151,"y":1226.25,"r":0,"sx":1,"sy":1,"skewX":0,"skewY":0},"3":{"x":172.8,"y":839.3,"name":"break1","type":"sprite","r":0,"sx":1,"sy":1,"a":1,"skewX":0,"skewY":0,"0":{"x":-207.9,"y":16.35,"name":"tower","type":"sprite","r":0,"sx":1.2354888916015625,"sy":1.39007568359375,"a":1,"skewX":0,"skewY":0,"0":{"type":"bitmap","libName":"towels_surround.png","x":0,"y":0,"r":0,"sx":1,"sy":1,"skewX":0,"skewY":0}},"1":{"x":0,"y":0,"name":"area","type":"sprite","r":0,"sx":4.090911865234375,"sy":3.8022613525390625,"a":1,"skewX":0,"skewY":0,"0":{"type":"bitmap","libName":"Bitmap 5","x":0,"y":0,"r":0,"sx":1,"sy":1.0000457763671875,"skewX":0,"skewY":0}},"2":{"type":"bitmap","libName":"breaker_qc.png copy 2","x":0,"y":0,"r":0,"sx":1.2633514404296875,"sy":1.2633514404296875,"skewX":0,"skewY":0}},"4":{"x":903.75,"y":670.5,"name":"ther","type":"sprite","r":0,"sx":1,"sy":1,"a":1,"skewX":0,"skewY":0,"0":{"x":-24.5,"y":252.35,"name":"ice","type":"sprite","r":0,"sx":0.91302490234375,"sy":0.8636322021484375,"a":0,"skewX":0,"skewY":0,"0":{"type":"bitmap","libName":"ice.png","x":0,"y":0,"r":0,"sx":1,"sy":1,"skewX":0,"skewY":0}},"1":{"x":223.6,"y":39.5,"name":"big","type":"sprite","r":0,"sx":1,"sy":1,"a":1,"skewX":0,"skewY":0,"0":{"x":0,"y":-2.7,"name":"waterColumn","type":"sprite","r":0,"sx":1,"sy":1,"a":1,"skewX":0,"skewY":0,"0":{"type":"bitmap","libName":"Bitmap 11.png","x":-6.25,"y":0,"r":0,"sx":2.50799560546875,"sy":18.179122924804688,"skewX":0,"skewY":0}},"1":{"x":-0.05,"y":0,"name":"bigTemp","type":"sprite","r":0,"sx":1,"sy":1,"a":1,"skewX":0,"skewY":0,"0":{"type":"bitmap","libName":"thermometer_big1.png","x":-65,"y":-1188.25,"r":0,"sx":1,"sy":1,"skewX":0,"skewY":0}},"2":{"x":4,"y":74.55,"name":"zoom","type":"sprite","r":0,"sx":1,"sy":1,"a":1,"skewX":0,"skewY":0,"0":{"x":0,"y":-89.5,"name":"eye","type":"sprite","r":0,"sx":1,"sy":1,"a":1,"skewX":0,"skewY":0,"0":{"type":"bitmap","libName":"Bitmap 8","x":0,"y":0,"r":0,"sx":1,"sy":1,"skewX":0,"skewY":0},"1":{"type":"bitmap","libName":"Bitmap 6","x":360.25,"y":-13.45,"r":0,"sx":1,"sy":1,"skewX":0,"skewY":0},"2":{"x":223.3,"y":-25.7,"w":188,"h":65.4,"name":"txt","type":"text","r":0,"txt":"n","a":"center","f":"45px '微软雅黑'","c":"#FFFFFF"}},"1":{"type":"bitmap","libName":"magnifier glass.png","x":-177.5,"y":-154.5,"r":0,"sx":1,"sy":1,"skewX":0,"skewY":0}}},"2":{"type":"bitmap","libName":"Bitmap 10.png","x":4.8,"y":395.95,"r":0,"sx":1,"sy":0.0293121337890625,"skewX":0,"skewY":0},"3":{"x":4.8,"y":396.4,"name":"waterColumn","type":"sprite","r":0,"sx":1,"sy":1,"a":1,"skewX":0,"skewY":0,"0":{"type":"bitmap","libName":"Bitmap 10.png","x":0,"y":-342,"r":0,"sx":1,"sy":1,"skewX":0,"skewY":0}},"4":{"x":-21.55,"y":365.45,"name":"bottom","type":"sprite","r":0,"sx":0.788330078125,"sy":0.973663330078125,"a":1,"skewX":0,"skewY":0,"0":{"type":"bitmap","libName":"Bitmap 5","x":0,"y":0,"r":0,"sx":1,"sy":1.0000457763671875,"skewX":0,"skewY":0}},"5":{"x":0,"y":407.55,"name":"head","type":"sprite","r":0,"sx":0.2144012451171875,"sy":0.3536376953125,"a":1,"skewX":0,"skewY":0,"0":{"type":"bitmap","libName":"Bitmap 5","x":0,"y":0,"r":0,"sx":1,"sy":1.0000457763671875,"skewX":0,"skewY":0}},"6":{"x":-35.1,"y":75.85,"name":"","type":"sprite","r":0,"sx":1,"sy":1,"a":1,"skewX":0,"skewY":0,"0":{"x":-27.9,"y":-22.5,"name":"area","type":"sprite","r":0,"sx":1.94122314453125,"sy":4.92242431640625,"a":1,"skewX":0,"skewY":0,"0":{"type":"bitmap","libName":"Bitmap 5","x":0,"y":0,"r":0,"sx":1,"sy":1.0000457763671875,"skewX":0,"skewY":0}},"1":{"type":"bitmap","libName":"Bitmap 4","x":5.3,"y":76.95,"r":0,"sx":1.04705810546875,"sy":1.04705810546875,"skewX":0,"skewY":0},"2":{"x":5.9,"y":79.3,"name":"shiguan","type":"sprite","r":0,"sx":1,"sy":1,"a":1,"skewX":0,"skewY":0,"0":{"type":"bitmap","libName":"Bitmap 3","x":0,"y":0,"r":0,"sx":1,"sy":1,"skewX":0,"skewY":0}},"3":{"x":10,"y":174.6,"name":"","type":"sprite","r":0,"sx":0.9071044921875,"sy":0.866241455078125,"a":0,"skewX":0,"skewY":0,"0":{"type":"bitmap","libName":"ice.png","x":0,"y":0,"r":0,"sx":1,"sy":1,"skewX":0,"skewY":0}}},"7":{"x":-48.05,"y":0,"name":"moveArea","type":"sprite","r":0,"sx":1.65667724609375,"sy":5.3107147216796875,"a":1,"skewX":0,"skewY":0,"0":{"type":"bitmap","libName":"Bitmap 5","x":0,"y":0,"r":0,"sx":1,"sy":1.0000457763671875,"skewX":0,"skewY":0}},"8":{"type":"bitmap","libName":"thermometer_up.png","x":0,"y":0,"r":0,"sx":1,"sy":1,"skewX":0,"skewY":0}}},{"type":"sprite","x":0,"y":0,"name":"frame1","0":{"type":"bitmap","libName":"Bitmap 18","x":315.7,"y":1252,"r":0,"sx":1,"sy":1,"skewX":0,"skewY":0},"1":{"x":544.55,"y":528.75,"name":"towerW","type":"sprite","r":0,"sx":1,"sy":1,"a":1,"skewX":0,"skewY":0,"0":{"type":"bitmap","libName":"Bitmap 13","x":0,"y":0,"r":0,"sx":1,"sy":1,"skewX":0,"skewY":0}},"2":{"x":197.4,"y":400.25,"name":"tower","type":"sprite","r":0,"sx":1,"sy":1,"a":1,"skewX":0,"skewY":0,"0":{"type":"bitmap","libName":"towels.png","x":0,"y":0,"r":0,"sx":1.3763275146484375,"sy":1.3763275146484375,"skewX":0,"skewY":0}},"3":{"x":246.65,"y":865.3,"name":"spoonHitRef","type":"sprite","r":0,"sx":3.744842529296875,"sy":4.0951385498046875,"a":1,"skewX":0,"skewY":0,"0":{"type":"bitmap","libName":"Bitmap 5","x":0,"y":0,"r":0,"sx":1,"sy":1.0000457763671875,"skewX":0,"skewY":0}},"4":{"x":752.4,"y":1056.4,"name":"mediAndSpoon","type":"sprite","r":0,"sx":1,"sy":1,"a":1,"skewX":0,"skewY":0,"linkageClassName":"nb.spoonAndMedicine","0":{"x":-355.95,"y":-232.5,"name":"spooncopey","type":"sprite","r":0,"sx":1,"sy":1,"a":1,"skewX":0,"skewY":0,"0":{"x":-35.6,"y":47.7,"name":"medicine","type":"nbMovie","r":0,"sx":1,"sy":1,"a":1,"skewX":0,"skewY":0,"0":{"index":1,"0":{"type":"bitmap","libName":"Bitmap 58","x":-27.4,"y":-33.45,"r":0,"sx":1,"sy":1,"skewX":0,"skewY":0}},"1":{"index":1,"0":{"x":0.05,"y":38.7,"name":"","type":"sprite","r":0,"sx":1,"sy":1,"a":1,"skewX":0,"skewY":0,"0":{"type":"bitmap","libName":"Bitmap 57","x":-15.4,"y":-32.95,"r":0,"sx":1,"sy":1,"skewX":0,"skewY":0}}},"2":{"index":1,"0":{"x":0.05,"y":64.05,"name":"","type":"sprite","r":0,"sx":0.953826904296875,"sy":1.07275390625,"a":1,"skewX":0,"skewY":0,"0":{"type":"bitmap","libName":"Bitmap 57","x":-15.4,"y":-32.95,"r":0,"sx":1,"sy":1,"skewX":0,"skewY":0}}},"3":{"index":1,"0":{"x":0.1,"y":89.35,"name":"","type":"sprite","r":0,"sx":0.76910400390625,"sy":1.3638916015625,"a":1,"skewX":0,"skewY":0,"0":{"type":"bitmap","libName":"Bitmap 57","x":-15.4,"y":-32.95,"r":0,"sx":1,"sy":1,"skewX":0,"skewY":0}}},"4":{"index":1,"0":{"x":0.05,"y":188.65,"name":"","type":"sprite","r":0,"sx":0.58441162109375,"sy":1.655029296875,"a":1,"skewX":0,"skewY":0,"0":{"type":"bitmap","libName":"Bitmap 57","x":-15.4,"y":-32.95,"r":0,"sx":1,"sy":1,"skewX":0,"skewY":0}}},"5":{"index":1,"0":{"type":"bitmap","libName":"Bitmap 59","x":-9.8,"y":194.2,"r":0,"sx":1,"sy":1,"skewX":0,"skewY":0}},"6":{"index":1,"0":{"type":"bitmap","libName":"Bitmap 63","x":-25.4,"y":226.6,"r":0,"sx":1,"sy":1,"skewX":0,"skewY":0}},"7":{"index":1,"0":{"type":"bitmap","libName":"Bitmap 62","x":-27.4,"y":241.35,"r":0,"sx":1,"sy":1,"skewX":0,"skewY":0}}},"1":{"type":"bitmap","libName":"spoon_1.png","x":-56.95,"y":-44.3,"r":0,"sx":0.9999847412109375,"sy":0.839996337890625,"skewX":0,"skewY":0}},"1":{"x":195,"y":71.9,"name":"spoon","type":"sprite","r":0,"sx":1,"sy":1,"a":1,"skewX":0,"skewY":0,"0":{"x":-35.6,"y":47.7,"name":"medicine","type":"nbMovie","r":0,"sx":1,"sy":1,"a":1,"skewX":0,"skewY":0,"0":{"index":1,"0":{"type":"bitmap","libName":"Bitmap 58","x":-27.4,"y":-33.45,"r":0,"sx":1,"sy":1,"skewX":0,"skewY":0}},"1":{"index":1,"0":{"x":0.05,"y":38.7,"name":"","type":"sprite","r":0,"sx":1,"sy":1,"a":1,"skewX":0,"skewY":0,"0":{"type":"bitmap","libName":"Bitmap 57","x":-15.4,"y":-32.95,"r":0,"sx":1,"sy":1,"skewX":0,"skewY":0}}},"2":{"index":1,"0":{"x":0.05,"y":64.05,"name":"","type":"sprite","r":0,"sx":0.953826904296875,"sy":1.07275390625,"a":1,"skewX":0,"skewY":0,"0":{"type":"bitmap","libName":"Bitmap 57","x":-15.4,"y":-32.95,"r":0,"sx":1,"sy":1,"skewX":0,"skewY":0}}},"3":{"index":1,"0":{"x":0.1,"y":89.35,"name":"","type":"sprite","r":0,"sx":0.76910400390625,"sy":1.3638916015625,"a":1,"skewX":0,"skewY":0,"0":{"type":"bitmap","libName":"Bitmap 57","x":-15.4,"y":-32.95,"r":0,"sx":1,"sy":1,"skewX":0,"skewY":0}}},"4":{"index":1,"0":{"x":0.05,"y":188.65,"name":"","type":"sprite","r":0,"sx":0.58441162109375,"sy":1.655029296875,"a":1,"skewX":0,"skewY":0,"0":{"type":"bitmap","libName":"Bitmap 57","x":-15.4,"y":-32.95,"r":0,"sx":1,"sy":1,"skewX":0,"skewY":0}}},"5":{"index":1,"0":{"type":"bitmap","libName":"Bitmap 59","x":-9.8,"y":194.2,"r":0,"sx":1,"sy":1,"skewX":0,"skewY":0}},"6":{"index":1,"0":{"type":"bitmap","libName":"Bitmap 63","x":-25.4,"y":226.6,"r":0,"sx":1,"sy":1,"skewX":0,"skewY":0}},"7":{"index":1,"0":{"type":"bitmap","libName":"Bitmap 62","x":-27.4,"y":241.35,"r":0,"sx":1,"sy":1,"skewX":0,"skewY":0}}},"1":{"type":"bitmap","libName":"spoon_1.png","x":-56.95,"y":-44.3,"r":0,"sx":0.9999847412109375,"sy":0.839996337890625,"skewX":0,"skewY":0}},"2":{"x":0,"y":0,"name":"medContainer","type":"sprite","r":0,"sx":1,"sy":1,"a":1,"skewX":0,"skewY":0,"0":{"type":"bitmap","libName":"glass_cup.png","x":0,"y":0,"r":0,"sx":1,"sy":1,"skewX":0,"skewY":0}}},"5":{"x":217.5,"y":907.6,"name":"break1","type":"sprite","r":0,"sx":1,"sy":1,"a":1,"skewX":0,"skewY":0,"0":{"x":-207.9,"y":16.35,"name":"tower","type":"sprite","r":0,"sx":1.2354888916015625,"sy":1.39007568359375,"a":1,"skewX":0,"skewY":0,"0":{"type":"bitmap","libName":"towels_surround.png","x":0,"y":0,"r":0,"sx":1,"sy":1,"skewX":0,"skewY":0}},"1":{"x":0,"y":0,"name":"area","type":"sprite","r":0,"sx":4.090911865234375,"sy":3.8022613525390625,"a":1,"skewX":0,"skewY":0,"0":{"type":"bitmap","libName":"Bitmap 5","x":0,"y":0,"r":0,"sx":1,"sy":1.0000457763671875,"skewX":0,"skewY":0}},"2":{"type":"bitmap","libName":"breaker_qc.png copy 2","x":0,"y":0,"r":0,"sx":1.2633514404296875,"sy":1.2633514404296875,"skewX":0,"skewY":0}},"6":{"x":1086.5,"y":854.7,"name":"ther","type":"sprite","r":0,"sx":1,"sy":1,"a":1,"skewX":0,"skewY":0,"0":{"x":-24.5,"y":252.35,"name":"ice","type":"sprite","r":0,"sx":0.91302490234375,"sy":0.8636322021484375,"a":0,"skewX":0,"skewY":0,"0":{"type":"bitmap","libName":"ice.png","x":0,"y":0,"r":0,"sx":1,"sy":1,"skewX":0,"skewY":0}},"1":{"x":223.6,"y":39.5,"name":"big","type":"sprite","r":0,"sx":1,"sy":1,"a":1,"skewX":0,"skewY":0,"0":{"x":0,"y":-2.7,"name":"waterColumn","type":"sprite","r":0,"sx":1,"sy":1,"a":1,"skewX":0,"skewY":0,"0":{"type":"bitmap","libName":"Bitmap 11.png","x":-6.25,"y":0,"r":0,"sx":2.50799560546875,"sy":18.179122924804688,"skewX":0,"skewY":0}},"1":{"x":-0.05,"y":0,"name":"bigTemp","type":"sprite","r":0,"sx":1,"sy":1,"a":1,"skewX":0,"skewY":0,"0":{"type":"bitmap","libName":"thermometer_big1.png","x":-65,"y":-1188.25,"r":0,"sx":1,"sy":1,"skewX":0,"skewY":0}},"2":{"x":4,"y":74.55,"name":"zoom","type":"sprite","r":0,"sx":1,"sy":1,"a":1,"skewX":0,"skewY":0,"0":{"x":0,"y":-89.5,"name":"eye","type":"sprite","r":0,"sx":1,"sy":1,"a":1,"skewX":0,"skewY":0,"0":{"type":"bitmap","libName":"Bitmap 8","x":0,"y":0,"r":0,"sx":1,"sy":1,"skewX":0,"skewY":0},"1":{"type":"bitmap","libName":"Bitmap 6","x":360.25,"y":-13.45,"r":0,"sx":1,"sy":1,"skewX":0,"skewY":0},"2":{"x":223.3,"y":-25.7,"w":188,"h":65.4,"name":"txt","type":"text","r":0,"txt":"n","a":"center","f":"45px '微软雅黑'","c":"#FFFFFF"}},"1":{"type":"bitmap","libName":"magnifier glass.png","x":-177.5,"y":-154.5,"r":0,"sx":1,"sy":1,"skewX":0,"skewY":0}}},"2":{"type":"bitmap","libName":"Bitmap 10.png","x":4.8,"y":395.95,"r":0,"sx":1,"sy":0.0293121337890625,"skewX":0,"skewY":0},"3":{"x":4.8,"y":396.4,"name":"waterColumn","type":"sprite","r":0,"sx":1,"sy":1,"a":1,"skewX":0,"skewY":0,"0":{"type":"bitmap","libName":"Bitmap 10.png","x":0,"y":-342,"r":0,"sx":1,"sy":1,"skewX":0,"skewY":0}},"4":{"x":-21.55,"y":365.45,"name":"bottom","type":"sprite","r":0,"sx":0.788330078125,"sy":0.973663330078125,"a":1,"skewX":0,"skewY":0,"0":{"type":"bitmap","libName":"Bitmap 5","x":0,"y":0,"r":0,"sx":1,"sy":1.0000457763671875,"skewX":0,"skewY":0}},"5":{"x":0,"y":407.55,"name":"head","type":"sprite","r":0,"sx":0.2144012451171875,"sy":0.3536376953125,"a":1,"skewX":0,"skewY":0,"0":{"type":"bitmap","libName":"Bitmap 5","x":0,"y":0,"r":0,"sx":1,"sy":1.0000457763671875,"skewX":0,"skewY":0}},"6":{"x":-35.1,"y":75.85,"name":"","type":"sprite","r":0,"sx":1,"sy":1,"a":1,"skewX":0,"skewY":0,"0":{"x":-27.9,"y":-22.5,"name":"area","type":"sprite","r":0,"sx":1.94122314453125,"sy":4.92242431640625,"a":1,"skewX":0,"skewY":0,"0":{"type":"bitmap","libName":"Bitmap 5","x":0,"y":0,"r":0,"sx":1,"sy":1.0000457763671875,"skewX":0,"skewY":0}},"1":{"type":"bitmap","libName":"Bitmap 4","x":5.3,"y":76.95,"r":0,"sx":1.04705810546875,"sy":1.04705810546875,"skewX":0,"skewY":0},"2":{"x":5.9,"y":79.3,"name":"shiguan","type":"sprite","r":0,"sx":1,"sy":1,"a":1,"skewX":0,"skewY":0,"0":{"type":"bitmap","libName":"Bitmap 3","x":0,"y":0,"r":0,"sx":1,"sy":1,"skewX":0,"skewY":0}},"3":{"x":10,"y":174.6,"name":"","type":"sprite","r":0,"sx":0.9071044921875,"sy":0.866241455078125,"a":0,"skewX":0,"skewY":0,"0":{"type":"bitmap","libName":"ice.png","x":0,"y":0,"r":0,"sx":1,"sy":1,"skewX":0,"skewY":0}}},"7":{"x":-48.05,"y":0,"name":"moveArea","type":"sprite","r":0,"sx":1.65667724609375,"sy":5.3107147216796875,"a":1,"skewX":0,"skewY":0,"0":{"type":"bitmap","libName":"Bitmap 5","x":0,"y":0,"r":0,"sx":1,"sy":1.0000457763671875,"skewX":0,"skewY":0}},"8":{"type":"bitmap","libName":"thermometer_up.png","x":0,"y":0,"r":0,"sx":1,"sy":1,"skewX":0,"skewY":0}}},{"type":"sprite","x":0,"y":0,"name":"frame0","0":{"x":932.55,"y":1077.95,"name":"therW","type":"sprite","r":0,"sx":1,"sy":1,"a":1,"skewX":0,"skewY":0,"0":{"type":"bitmap","libName":"Bitmap 11","x":0,"y":0,"r":0,"sx":1,"sy":1,"skewX":0,"skewY":0}},"1":{"type":"bitmap","libName":"Bitmap 10","x":352,"y":1087.55,"r":0,"sx":1,"sy":1,"skewX":0,"skewY":0},"2":{"x":994.65,"y":640.3,"name":"ther","type":"sprite","r":0,"sx":1,"sy":1,"a":1,"skewX":0,"skewY":0,"0":{"x":223.6,"y":39.5,"name":"big","type":"sprite","r":0,"sx":1,"sy":1,"a":1,"skewX":0,"skewY":0,"0":{"x":0,"y":-2.7,"name":"waterColumn","type":"sprite","r":0,"sx":1,"sy":1,"a":1,"skewX":0,"skewY":0,"0":{"type":"bitmap","libName":"Bitmap 11.png","x":-6.25,"y":0,"r":0,"sx":2.50799560546875,"sy":18.179122924804688,"skewX":0,"skewY":0}},"1":{"x":-0.05,"y":0,"name":"bigTemp","type":"sprite","r":0,"sx":1,"sy":1,"a":1,"skewX":0,"skewY":0,"0":{"type":"bitmap","libName":"thermometer_big1.png","x":-65,"y":-1188.25,"r":0,"sx":1,"sy":1,"skewX":0,"skewY":0}},"2":{"x":4,"y":74.55,"name":"zoom","type":"sprite","r":0,"sx":1,"sy":1,"a":1,"skewX":0,"skewY":0,"0":{"x":0,"y":-89.5,"name":"eye","type":"sprite","r":0,"sx":1,"sy":1,"a":1,"skewX":0,"skewY":0,"0":{"type":"bitmap","libName":"Bitmap 8","x":0,"y":0,"r":0,"sx":1,"sy":1,"skewX":0,"skewY":0},"1":{"type":"bitmap","libName":"Bitmap 6","x":360.25,"y":-13.45,"r":0,"sx":1,"sy":1,"skewX":0,"skewY":0},"2":{"x":223.3,"y":-25.7,"w":188,"h":65.4,"name":"txt","type":"text","r":0,"txt":"n","a":"center","f":"45px '微软雅黑'","c":"#FFFFFF"}},"1":{"type":"bitmap","libName":"magnifier glass.png","x":-177.5,"y":-154.5,"r":0,"sx":1,"sy":1,"skewX":0,"skewY":0}}},"1":{"type":"bitmap","libName":"Bitmap 10.png","x":4.8,"y":395.95,"r":0,"sx":1,"sy":0.0293121337890625,"skewX":0,"skewY":0},"2":{"x":4.8,"y":396.4,"name":"waterColumn","type":"sprite","r":0,"sx":1,"sy":1,"a":1,"skewX":0,"skewY":0,"0":{"type":"bitmap","libName":"Bitmap 10.png","x":0,"y":-342,"r":0,"sx":1,"sy":1,"skewX":0,"skewY":0}},"3":{"x":-21.55,"y":365.45,"name":"bottom","type":"sprite","r":0,"sx":0.788330078125,"sy":0.973663330078125,"a":1,"skewX":0,"skewY":0,"0":{"type":"bitmap","libName":"Bitmap 5","x":0,"y":0,"r":0,"sx":1,"sy":1.0000457763671875,"skewX":0,"skewY":0}},"4":{"x":0,"y":407.55,"name":"head","type":"sprite","r":0,"sx":0.2144012451171875,"sy":0.3536376953125,"a":1,"skewX":0,"skewY":0,"0":{"type":"bitmap","libName":"Bitmap 5","x":0,"y":0,"r":0,"sx":1,"sy":1.0000457763671875,"skewX":0,"skewY":0}},"5":{"x":-3,"y":0,"name":"moveArea","type":"sprite","r":0,"sx":1.65667724609375,"sy":5.3107147216796875,"a":1,"skewX":0,"skewY":0,"0":{"type":"bitmap","libName":"Bitmap 5","x":0,"y":0,"r":0,"sx":1,"sy":1.0000457763671875,"skewX":0,"skewY":0}},"6":{"type":"bitmap","libName":"thermometer.png copy","x":-13.35,"y":-21.5,"r":0,"sx":1.01580810546875,"sy":1.01580810546875,"skewX":0,"skewY":0}},"3":{"x":379.9,"y":628.65,"name":"break1","type":"sprite","r":0,"sx":1,"sy":1,"a":1,"skewX":0,"skewY":0,"0":{"x":-27.9,"y":-22.5,"name":"area","type":"sprite","r":0,"sx":1.94122314453125,"sy":4.92242431640625,"a":1,"skewX":0,"skewY":0,"0":{"type":"bitmap","libName":"Bitmap 5","x":0,"y":0,"r":0,"sx":1,"sy":1.0000457763671875,"skewX":0,"skewY":0}},"1":{"type":"bitmap","libName":"Bitmap 4","x":5.3,"y":76.95,"r":0,"sx":1.04705810546875,"sy":1.04705810546875,"skewX":0,"skewY":0},"2":{"x":5.9,"y":79.3,"name":"shiguan","type":"sprite","r":0,"sx":1,"sy":1,"a":1,"skewX":0,"skewY":0,"0":{"type":"bitmap","libName":"Bitmap 3","x":0,"y":0,"r":0,"sx":1,"sy":1,"skewX":0,"skewY":0}},"3":{"x":10,"y":174.6,"name":"","type":"sprite","r":0,"sx":0.9071044921875,"sy":0.866241455078125,"a":0,"skewX":0,"skewY":0,"0":{"type":"bitmap","libName":"ice.png","x":0,"y":0,"r":0,"sx":1,"sy":1,"skewX":0,"skewY":0}}}},{"type":"sprite","x":0,"y":0,"name":"ee","0":{"type":"bitmap","libName":"煤油温度计_qc.png","x":176.2,"y":1228.2,"r":0,"sx":1,"sy":1,"skewX":0,"skewY":0},"1":{"type":"bitmap","libName":"Bitmap 4","x":967.2,"y":182.1,"r":0.003967311075891041,"sx":0.66461181640625,"sy":0.66461181640625,"skewX":0.003967311075891041,"skewY":0.003967311075891041},"2":{"type":"bitmap","libName":"Bitmap 3","x":967.55,"y":183.55,"r":0.003967311075891041,"sx":0.634765625,"sy":0.634765625,"skewX":0.003967311075891041,"skewY":0.003967311075891041},"3":{"type":"bitmap","libName":"salt_qc.png copy","x":927.45,"y":984.9,"r":0,"sx":1,"sy":1,"skewX":0,"skewY":0},"4":{"type":"bitmap","libName":"食用盐_qc.png copy","x":927.45,"y":1228.2,"r":0,"sx":1,"sy":1,"skewX":0,"skewY":0},"5":{"type":"bitmap","libName":"thermometer_qc.png copy","x":169.2,"y":1057.9,"r":0,"sx":1,"sy":1,"skewX":0,"skewY":0},"6":{"type":"bitmap","libName":"spoon_qc.png copy","x":874.6,"y":642.9,"r":0,"sx":1,"sy":1,"skewX":0,"skewY":0},"7":{"type":"bitmap","libName":"钢勺_qc.png copy","x":943.45,"y":841.75,"r":0,"sx":1,"sy":1,"skewX":0,"skewY":0},"8":{"type":"bitmap","libName":"towels_qc.png copy","x":181.2,"y":732.9,"r":0,"sx":1,"sy":1,"skewX":0,"skewY":0},"9":{"type":"bitmap","libName":"毛巾_qc.png copy","x":332.2,"y":841.75,"r":0,"sx":1,"sy":1,"skewX":0,"skewY":0},"10":{"type":"bitmap","libName":"breaker_qc.png copy","x":245.2,"y":163.4,"r":0,"sx":1,"sy":1,"skewX":0,"skewY":0},"11":{"type":"bitmap","libName":"装满碎冰的烧杯_qc.png copy","x":245.2,"y":478.25,"r":0,"sx":1,"sy":1,"skewX":0,"skewY":0},"12":{"type":"bitmap","libName":"试管_qc.png copy","x":834.4,"y":480.25,"r":0,"sx":1,"sy":1,"skewX":0,"skewY":0}},{"name":"ei","x":0,"y":0,"type":"sprite"},{"name":"cc","x":0,"y":0,"type":"sprite"}]