[{"type":"sprite","x":0,"y":0,"name":"frame0","0":{"x":609.4,"y":547.8,"name":"twos","type":"sprite","r":0,"sx":1,"sy":0.9682464599609375,"a":1,"skewX":0,"skewY":0,"0":{"type":"bitmap","libName":"Bitmap 5","x":0,"y":0,"r":0,"sx":1.094451904296875,"sy":1.04998779296875,"skewX":0,"skewY":0}},"1":{"x":609.4,"y":542.8,"name":"showhide","type":"sprite","r":0,"sx":1,"sy":0.9682464599609375,"a":1,"skewX":0,"skewY":0,"0":{"type":"bitmap","libName":"Bitmap 4","x":0,"y":5.25,"r":0,"sx":1.19390869140625,"sy":1.0677947998046875,"skewX":0,"skewY":0}},"2":{"x":709.6,"y":473.5,"name":"waxPiece1","type":"nbMovie","r":0,"sx":1,"sy":1,"a":1,"skewX":0,"skewY":0,"0":{"index":1,"0":{"type":"bitmap","libName":"a0001.png","x":0,"y":75.45,"r":0,"sx":1,"sy":1,"skewX":0,"skewY":0}},"1":{"index":1,"0":{"type":"bitmap","libName":"a0002.png","x":0,"y":75.45,"r":0,"sx":1,"sy":1,"skewX":0,"skewY":0}},"2":{"index":1,"0":{"type":"bitmap","libName":"a0003.png","x":0,"y":75.45,"r":0,"sx":1,"sy":1,"skewX":0,"skewY":0}},"3":{"index":1,"0":{"type":"bitmap","libName":"a0004.png","x":0,"y":75.45,"r":0,"sx":1,"sy":1,"skewX":0,"skewY":0}},"4":{"index":1,"0":{"type":"bitmap","libName":"a0005.png","x":0,"y":75.45,"r":0,"sx":1,"sy":1,"skewX":0,"skewY":0}},"5":{"index":1,"0":{"type":"bitmap","libName":"a0006.png","x":0,"y":75.45,"r":0,"sx":1,"sy":1,"skewX":0,"skewY":0}},"6":{"index":1,"0":{"type":"bitmap","libName":"a0007.png","x":0,"y":75.45,"r":0,"sx":1,"sy":1,"skewX":0,"skewY":0}},"7":{"index":1,"0":{"type":"bitmap","libName":"a0008.png","x":0,"y":75.45,"r":0,"sx":1,"sy":1,"skewX":0,"skewY":0}},"8":{"index":1,"0":{"type":"bitmap","libName":"a0009.png","x":0,"y":75.45,"r":0,"sx":1,"sy":1,"skewX":0,"skewY":0}},"9":{"index":1,"0":{"type":"bitmap","libName":"a0010.png","x":0,"y":75.45,"r":0,"sx":1,"sy":1,"skewX":0,"skewY":0}},"10":{"index":1,"0":{"type":"bitmap","libName":"a0011.png","x":0,"y":75.45,"r":0,"sx":1,"sy":1,"skewX":0,"skewY":0}},"11":{"index":1,"0":{"type":"bitmap","libName":"a0012.png","x":0,"y":75.45,"r":0,"sx":1,"sy":1,"skewX":0,"skewY":0}},"12":{"index":1,"0":{"type":"bitmap","libName":"a0013.png","x":0,"y":75.45,"r":0,"sx":1,"sy":1,"skewX":0,"skewY":0}},"13":{"index":1,"0":{"type":"bitmap","libName":"a0014.png","x":0,"y":75.45,"r":0,"sx":1,"sy":1,"skewX":0,"skewY":0}},"14":{"index":1,"0":{"type":"bitmap","libName":"a0015.png","x":0,"y":75.45,"r":0,"sx":1,"sy":1,"skewX":0,"skewY":0}},"15":{"index":1,"0":{"type":"bitmap","libName":"a0016.png","x":0,"y":75.45,"r":0,"sx":1,"sy":1,"skewX":0,"skewY":0}},"16":{"index":1,"0":{"type":"bitmap","libName":"a0017.png","x":0,"y":75.45,"r":0,"sx":1,"sy":1,"skewX":0,"skewY":0}},"17":{"index":1,"0":{"type":"bitmap","libName":"a0018.png","x":0,"y":75.45,"r":0,"sx":1,"sy":1,"skewX":0,"skewY":0}},"18":{"index":1,"0":{"type":"bitmap","libName":"a0019.png","x":0,"y":75.45,"r":0,"sx":1,"sy":1,"skewX":0,"skewY":0}},"19":{"index":1,"0":{"type":"bitmap","libName":"a0020.png","x":0,"y":75.45,"r":0,"sx":1,"sy":1,"skewX":0,"skewY":0}},"20":{"index":1,"0":{"type":"bitmap","libName":"a0021.png","x":0,"y":75.45,"r":0,"sx":1,"sy":1,"skewX":0,"skewY":0}},"21":{"index":1,"0":{"type":"bitmap","libName":"a0022.png","x":0,"y":75.45,"r":0,"sx":1,"sy":1,"skewX":0,"skewY":0}},"22":{"index":1,"0":{"type":"bitmap","libName":"a0023.png","x":0,"y":75.45,"r":0,"sx":1,"sy":1,"skewX":0,"skewY":0}},"23":{"index":1,"0":{"type":"bitmap","libName":"a0024.png","x":0,"y":75.45,"r":0,"sx":1,"sy":1,"skewX":0,"skewY":0}},"24":{"index":1,"0":{"type":"bitmap","libName":"a0025.png","x":0,"y":75.45,"r":0,"sx":1,"sy":1,"skewX":0,"skewY":0}},"25":{"index":1,"0":{"type":"bitmap","libName":"a0026.png","x":0,"y":75.45,"r":0,"sx":1,"sy":1,"skewX":0,"skewY":0}},"26":{"index":1,"0":{"type":"bitmap","libName":"a0027.png","x":0,"y":75.45,"r":0,"sx":1,"sy":1,"skewX":0,"skewY":0}},"27":{"index":1,"0":{"type":"bitmap","libName":"a0028.png","x":0,"y":75.45,"r":0,"sx":1,"sy":1,"skewX":0,"skewY":0}},"28":{"index":1,"0":{"type":"bitmap","libName":"a0029.png","x":0,"y":75.45,"r":0,"sx":1,"sy":1,"skewX":0,"skewY":0}},"29":{"index":1,"0":{"type":"bitmap","libName":"a0030.png","x":0,"y":75.45,"r":0,"sx":1,"sy":1,"skewX":0,"skewY":0}},"30":{"index":1,"0":{"type":"bitmap","libName":"a0031.png","x":0,"y":75.45,"r":0,"sx":1,"sy":1,"skewX":0,"skewY":0}},"31":{"index":1,"0":{"type":"bitmap","libName":"a0032.png","x":0,"y":75.45,"r":0,"sx":1,"sy":1,"skewX":0,"skewY":0}},"32":{"index":1,"0":{"type":"bitmap","libName":"a0033.png","x":0,"y":75.45,"r":0,"sx":1,"sy":1,"skewX":0,"skewY":0}},"33":{"index":1,"0":{"type":"bitmap","libName":"a0034.png","x":0,"y":75.45,"r":0,"sx":1,"sy":1,"skewX":0,"skewY":0}},"34":{"index":1,"0":{"type":"bitmap","libName":"a0035.png","x":0,"y":75.45,"r":0,"sx":1,"sy":1,"skewX":0,"skewY":0}},"35":{"index":1,"0":{"type":"bitmap","libName":"a0036.png","x":0,"y":75.45,"r":0,"sx":1,"sy":1,"skewX":0,"skewY":0}},"36":{"index":1,"0":{"type":"bitmap","libName":"a0037.png","x":0,"y":75.45,"r":0,"sx":1,"sy":1,"skewX":0,"skewY":0}},"37":{"index":1,"0":{"type":"bitmap","libName":"a0038.png","x":0,"y":75.45,"r":0,"sx":1,"sy":1,"skewX":0,"skewY":0}},"38":{"index":1,"0":{"type":"bitmap","libName":"a0039.png","x":0,"y":75.45,"r":0,"sx":1,"sy":1,"skewX":0,"skewY":0}},"39":{"index":1,"0":{"type":"bitmap","libName":"a0040.png","x":0,"y":75.45,"r":0,"sx":1,"sy":1,"skewX":0,"skewY":0}},"40":{"index":1,"0":{"type":"bitmap","libName":"a0041.png","x":0,"y":75.45,"r":0,"sx":1,"sy":1,"skewX":0,"skewY":0}},"41":{"index":1,"0":{"type":"bitmap","libName":"a0042.png","x":0,"y":75.45,"r":0,"sx":1,"sy":1,"skewX":0,"skewY":0}},"42":{"index":1,"0":{"type":"bitmap","libName":"a0043.png","x":0,"y":75.45,"r":0,"sx":1,"sy":1,"skewX":0,"skewY":0}},"43":{"index":1,"0":{"type":"bitmap","libName":"a0044.png","x":0,"y":75.45,"r":0,"sx":1,"sy":1,"skewX":0,"skewY":0}}},"3":{"x":609.4,"y":545.95,"name":"lkMask","type":"sprite","r":0,"sx":1,"sy":1,"a":1,"skewX":0,"skewY":0,"0":{"type":"shape","path":[255,32.5,245,45.95,245,55.45,209.1,3,55.45,209.1,65,173.25,65,122.5,3,65,122.5,65,71.75,55.45,35.85,3,55.45,35.85,45.95,0,32.5,0,3,32.5,0,19.05,0,9.5,35.85,3,9.5,35.85,0,71.75,0,122.5,3,0,122.5,0,173.25,9.5,209.1,3,9.5,209.1,19.05,245,32.5,245,3,1,16763734,33]}},"4":{"x":609.4,"y":472.3,"name":"waxPiece","type":"nbMovie","r":0,"sx":1,"sy":1,"a":1,"skewX":0,"skewY":0,"0":{"index":1,"0":{"type":"bitmap","libName":"a0001.png","x":0,"y":75.45,"r":0,"sx":1,"sy":1,"skewX":0,"skewY":0}},"1":{"index":1,"0":{"type":"bitmap","libName":"a0002.png","x":0,"y":75.45,"r":0,"sx":1,"sy":1,"skewX":0,"skewY":0}},"2":{"index":1,"0":{"type":"bitmap","libName":"a0003.png","x":0,"y":75.45,"r":0,"sx":1,"sy":1,"skewX":0,"skewY":0}},"3":{"index":1,"0":{"type":"bitmap","libName":"a0004.png","x":0,"y":75.45,"r":0,"sx":1,"sy":1,"skewX":0,"skewY":0}},"4":{"index":1,"0":{"type":"bitmap","libName":"a0005.png","x":0,"y":75.45,"r":0,"sx":1,"sy":1,"skewX":0,"skewY":0}},"5":{"index":1,"0":{"type":"bitmap","libName":"a0006.png","x":0,"y":75.45,"r":0,"sx":1,"sy":1,"skewX":0,"skewY":0}},"6":{"index":1,"0":{"type":"bitmap","libName":"a0007.png","x":0,"y":75.45,"r":0,"sx":1,"sy":1,"skewX":0,"skewY":0}},"7":{"index":1,"0":{"type":"bitmap","libName":"a0008.png","x":0,"y":75.45,"r":0,"sx":1,"sy":1,"skewX":0,"skewY":0}},"8":{"index":1,"0":{"type":"bitmap","libName":"a0009.png","x":0,"y":75.45,"r":0,"sx":1,"sy":1,"skewX":0,"skewY":0}},"9":{"index":1,"0":{"type":"bitmap","libName":"a0010.png","x":0,"y":75.45,"r":0,"sx":1,"sy":1,"skewX":0,"skewY":0}},"10":{"index":1,"0":{"type":"bitmap","libName":"a0011.png","x":0,"y":75.45,"r":0,"sx":1,"sy":1,"skewX":0,"skewY":0}},"11":{"index":1,"0":{"type":"bitmap","libName":"a0012.png","x":0,"y":75.45,"r":0,"sx":1,"sy":1,"skewX":0,"skewY":0}},"12":{"index":1,"0":{"type":"bitmap","libName":"a0013.png","x":0,"y":75.45,"r":0,"sx":1,"sy":1,"skewX":0,"skewY":0}},"13":{"index":1,"0":{"type":"bitmap","libName":"a0014.png","x":0,"y":75.45,"r":0,"sx":1,"sy":1,"skewX":0,"skewY":0}},"14":{"index":1,"0":{"type":"bitmap","libName":"a0015.png","x":0,"y":75.45,"r":0,"sx":1,"sy":1,"skewX":0,"skewY":0}},"15":{"index":1,"0":{"type":"bitmap","libName":"a0016.png","x":0,"y":75.45,"r":0,"sx":1,"sy":1,"skewX":0,"skewY":0}},"16":{"index":1,"0":{"type":"bitmap","libName":"a0017.png","x":0,"y":75.45,"r":0,"sx":1,"sy":1,"skewX":0,"skewY":0}},"17":{"index":1,"0":{"type":"bitmap","libName":"a0018.png","x":0,"y":75.45,"r":0,"sx":1,"sy":1,"skewX":0,"skewY":0}},"18":{"index":1,"0":{"type":"bitmap","libName":"a0019.png","x":0,"y":75.45,"r":0,"sx":1,"sy":1,"skewX":0,"skewY":0}},"19":{"index":1,"0":{"type":"bitmap","libName":"a0020.png","x":0,"y":75.45,"r":0,"sx":1,"sy":1,"skewX":0,"skewY":0}},"20":{"index":1,"0":{"type":"bitmap","libName":"a0021.png","x":0,"y":75.45,"r":0,"sx":1,"sy":1,"skewX":0,"skewY":0}},"21":{"index":1,"0":{"type":"bitmap","libName":"a0022.png","x":0,"y":75.45,"r":0,"sx":1,"sy":1,"skewX":0,"skewY":0}},"22":{"index":1,"0":{"type":"bitmap","libName":"a0023.png","x":0,"y":75.45,"r":0,"sx":1,"sy":1,"skewX":0,"skewY":0}},"23":{"index":1,"0":{"type":"bitmap","libName":"a0024.png","x":0,"y":75.45,"r":0,"sx":1,"sy":1,"skewX":0,"skewY":0}},"24":{"index":1,"0":{"type":"bitmap","libName":"a0025.png","x":0,"y":75.45,"r":0,"sx":1,"sy":1,"skewX":0,"skewY":0}},"25":{"index":1,"0":{"type":"bitmap","libName":"a0026.png","x":0,"y":75.45,"r":0,"sx":1,"sy":1,"skewX":0,"skewY":0}},"26":{"index":1,"0":{"type":"bitmap","libName":"a0027.png","x":0,"y":75.45,"r":0,"sx":1,"sy":1,"skewX":0,"skewY":0}},"27":{"index":1,"0":{"type":"bitmap","libName":"a0028.png","x":0,"y":75.45,"r":0,"sx":1,"sy":1,"skewX":0,"skewY":0}},"28":{"index":1,"0":{"type":"bitmap","libName":"a0029.png","x":0,"y":75.45,"r":0,"sx":1,"sy":1,"skewX":0,"skewY":0}},"29":{"index":1,"0":{"type":"bitmap","libName":"a0030.png","x":0,"y":75.45,"r":0,"sx":1,"sy":1,"skewX":0,"skewY":0}},"30":{"index":1,"0":{"type":"bitmap","libName":"a0031.png","x":0,"y":75.45,"r":0,"sx":1,"sy":1,"skewX":0,"skewY":0}},"31":{"index":1,"0":{"type":"bitmap","libName":"a0032.png","x":0,"y":75.45,"r":0,"sx":1,"sy":1,"skewX":0,"skewY":0}},"32":{"index":1,"0":{"type":"bitmap","libName":"a0033.png","x":0,"y":75.45,"r":0,"sx":1,"sy":1,"skewX":0,"skewY":0}},"33":{"index":1,"0":{"type":"bitmap","libName":"a0034.png","x":0,"y":75.45,"r":0,"sx":1,"sy":1,"skewX":0,"skewY":0}},"34":{"index":1,"0":{"type":"bitmap","libName":"a0035.png","x":0,"y":75.45,"r":0,"sx":1,"sy":1,"skewX":0,"skewY":0}},"35":{"index":1,"0":{"type":"bitmap","libName":"a0036.png","x":0,"y":75.45,"r":0,"sx":1,"sy":1,"skewX":0,"skewY":0}},"36":{"index":1,"0":{"type":"bitmap","libName":"a0037.png","x":0,"y":75.45,"r":0,"sx":1,"sy":1,"skewX":0,"skewY":0}},"37":{"index":1,"0":{"type":"bitmap","libName":"a0038.png","x":0,"y":75.45,"r":0,"sx":1,"sy":1,"skewX":0,"skewY":0}},"38":{"index":1,"0":{"type":"bitmap","libName":"a0039.png","x":0,"y":75.45,"r":0,"sx":1,"sy":1,"skewX":0,"skewY":0}},"39":{"index":1,"0":{"type":"bitmap","libName":"a0040.png","x":0,"y":75.45,"r":0,"sx":1,"sy":1,"skewX":0,"skewY":0}},"40":{"index":1,"0":{"type":"bitmap","libName":"a0041.png","x":0,"y":75.45,"r":0,"sx":1,"sy":1,"skewX":0,"skewY":0}},"41":{"index":1,"0":{"type":"bitmap","libName":"a0042.png","x":0,"y":75.45,"r":0,"sx":1,"sy":1,"skewX":0,"skewY":0}},"42":{"index":1,"0":{"type":"bitmap","libName":"a0043.png","x":0,"y":75.45,"r":0,"sx":1,"sy":1,"skewX":0,"skewY":0}},"43":{"index":1,"0":{"type":"bitmap","libName":"a0044.png","x":0,"y":75.45,"r":0,"sx":1,"sy":1,"skewX":0,"skewY":0}}},"5":{"x":607.4,"y":584.2,"name":"ref","type":"sprite","r":0,"sx":1,"sy":1,"a":0,"skewX":0,"skewY":0,"0":{"type":"bitmap","libName":"Bitmap 1","x":0,"y":0,"r":0,"sx":1,"sy":1,"skewX":0,"skewY":0}},"6":{"x":1003.85,"y":1137.75,"name":"ww1","type":"sprite","r":0,"sx":1,"sy":1,"a":1,"skewX":0,"skewY":0,"0":{"x":0,"y":0,"w":74.2,"h":50.2,"name":"","type":"text","r":0,"txt":"火柴","a":"left","f":"35px '微软雅黑'","c":"#FFFFFF"}},"7":{"x":631.95,"y":1137.75,"name":"ww0","type":"sprite","r":0,"sx":1,"sy":1,"a":1,"skewX":0,"skewY":0,"0":{"x":0,"y":0,"w":109.2,"h":50.2,"name":"","type":"text","r":0,"txt":"酒精灯","a":"left","f":"35px '微软雅黑'","c":"#FFFFFF"}},"8":{"x":886.45,"y":674.15,"name":"bb","type":"sprite","r":0,"sx":1,"sy":1,"a":1,"skewX":0,"skewY":0,"linkageClassName":"nb.spiritFunc","0":{"x":-1,"y":-29.95,"name":"corver","type":"sprite","r":0,"sx":1,"sy":1,"a":1,"skewX":0,"skewY":0,"0":{"type":"bitmap","libName":"hat.png","x":-23.5,"y":0,"r":0,"sx":1,"sy":1,"skewX":0,"skewY":0},"1":{"type":"shape","path":[255,-14,-44.85,2,-14,5.15,2,36,5.15,2,36,-44.85,-7.2,-36.45,-14,-44.85,3,0,3750201,33]},"2":{"x":-57.8,"y":-29,"name":"","type":"sprite","r":0,"sx":2.33831787109375,"sy":2.259246826171875,"a":1,"skewX":0,"skewY":0,"0":{"type":"bitmap","libName":"hitArea.png","x":0,"y":0,"r":0,"sx":1,"sy":1,"skewX":0,"skewY":0}}},"1":{"x":-26,"y":-100.1,"name":"fireArea","type":"sprite","r":0,"sx":1,"sy":2.28125,"a":1,"skewX":0,"skewY":0,"0":{"type":"bitmap","libName":"hitArea.png","x":0,"y":0,"r":0,"sx":1,"sy":1,"skewX":0,"skewY":0}},"2":{"x":-26,"y":-22.6,"name":"head","type":"sprite","r":0,"sx":1,"sy":1.17108154296875,"a":1,"skewX":0,"skewY":0,"0":{"type":"bitmap","libName":"hitArea.png","x":0,"y":0,"r":0,"sx":1,"sy":1,"skewX":0,"skewY":0}},"3":{"x":0,"y":0,"name":"body","type":"sprite","r":0,"sx":1,"sy":1,"a":1,"skewX":0,"skewY":0,"0":{"type":"bitmap","libName":"cup.png","x":-70,"y":0,"r":0,"sx":1,"sy":1,"skewX":0,"skewY":0}}},"9":{"x":725.45,"y":674.15,"name":"aa","type":"sprite","r":0,"sx":1,"sy":1,"a":1,"skewX":0,"skewY":0,"linkageClassName":"nb.spiritFunc","0":{"x":-1,"y":-29.95,"name":"corver","type":"sprite","r":0,"sx":1,"sy":1,"a":1,"skewX":0,"skewY":0,"0":{"type":"bitmap","libName":"hat.png","x":-23.5,"y":0,"r":0,"sx":1,"sy":1,"skewX":0,"skewY":0},"1":{"type":"shape","path":[255,-14,-44.85,2,-14,5.15,2,36,5.15,2,36,-44.85,-7.2,-36.45,-14,-44.85,3,0,3750201,33]},"2":{"x":-57.8,"y":-29,"name":"","type":"sprite","r":0,"sx":2.33831787109375,"sy":2.259246826171875,"a":1,"skewX":0,"skewY":0,"0":{"type":"bitmap","libName":"hitArea.png","x":0,"y":0,"r":0,"sx":1,"sy":1,"skewX":0,"skewY":0}}},"1":{"x":-26,"y":-100.1,"name":"fireArea","type":"sprite","r":0,"sx":1,"sy":2.28125,"a":1,"skewX":0,"skewY":0,"0":{"type":"bitmap","libName":"hitArea.png","x":0,"y":0,"r":0,"sx":1,"sy":1,"skewX":0,"skewY":0}},"2":{"x":-26,"y":-22.6,"name":"head","type":"sprite","r":0,"sx":1,"sy":1.17108154296875,"a":1,"skewX":0,"skewY":0,"0":{"type":"bitmap","libName":"hitArea.png","x":0,"y":0,"r":0,"sx":1,"sy":1,"skewX":0,"skewY":0}},"3":{"x":0,"y":0,"name":"body","type":"sprite","r":0,"sx":1,"sy":1,"a":1,"skewX":0,"skewY":0,"0":{"type":"bitmap","libName":"cup.png","x":-70,"y":0,"r":0,"sx":1,"sy":1,"skewX":0,"skewY":0}}},"10":{"x":962.25,"y":828.15,"name":"match","type":"sprite","r":0,"sx":1,"sy":1,"a":1,"skewX":0,"skewY":0,"0":{"x":-15,"y":25.05,"name":"fireArea","type":"sprite","r":0,"sx":1,"sy":1,"a":1,"skewX":0,"skewY":0,"0":{"type":"bitmap","libName":"hitArea.png","x":0,"y":0,"r":0,"sx":1,"sy":1,"skewX":0,"skewY":0}},"1":{"type":"bitmap","libName":"hitArea.png","x":-15,"y":-21,"r":0,"sx":3.1609954833984375,"sy":1.9210052490234375,"skewX":0,"skewY":0},"2":{"type":"bitmap","libName":"match.png","x":0,"y":0,"r":0,"sx":1,"sy":1,"skewX":0,"skewY":0}},"11":{"x":912.3,"y":941.15,"name":"matches","type":"sprite","r":0,"sx":1,"sy":1,"a":1,"skewX":0,"skewY":0,"linkageClassName":"nb.matches","0":{"type":"bitmap","libName":"match_box.png","x":0,"y":0,"r":0,"sx":1,"sy":1,"skewX":0,"skewY":0}},"12":{"x":677.4,"y":969.15,"name":"spiritLamp","type":"sprite","r":0,"sx":1,"sy":1,"a":1,"skewX":0,"skewY":0,"linkageClassName":"nb.spiritFunc","0":{"x":-1,"y":-29.95,"name":"corver","type":"sprite","r":0,"sx":1,"sy":1,"a":1,"skewX":0,"skewY":0,"0":{"type":"bitmap","libName":"hat.png","x":-23.5,"y":0,"r":0,"sx":1,"sy":1,"skewX":0,"skewY":0},"1":{"type":"shape","path":[255,-14,-44.85,2,-14,5.15,2,36,5.15,2,36,-44.85,-7.2,-36.45,-14,-44.85,3,0,3750201,33]},"2":{"x":-57.8,"y":-29,"name":"","type":"sprite","r":0,"sx":2.33831787109375,"sy":2.259246826171875,"a":1,"skewX":0,"skewY":0,"0":{"type":"bitmap","libName":"hitArea.png","x":0,"y":0,"r":0,"sx":1,"sy":1,"skewX":0,"skewY":0}}},"1":{"x":-26,"y":-100.1,"name":"fireArea","type":"sprite","r":0,"sx":1,"sy":2.28125,"a":1,"skewX":0,"skewY":0,"0":{"type":"bitmap","libName":"hitArea.png","x":0,"y":0,"r":0,"sx":1,"sy":1,"skewX":0,"skewY":0}},"2":{"x":-26,"y":-22.6,"name":"head","type":"sprite","r":0,"sx":1,"sy":1.17108154296875,"a":1,"skewX":0,"skewY":0,"0":{"type":"bitmap","libName":"hitArea.png","x":0,"y":0,"r":0,"sx":1,"sy":1,"skewX":0,"skewY":0}},"3":{"x":0,"y":0,"name":"body","type":"sprite","r":0,"sx":1,"sy":1,"a":1,"skewX":0,"skewY":0,"0":{"type":"bitmap","libName":"cup.png","x":-70,"y":0,"r":0,"sx":1,"sy":1,"skewX":0,"skewY":0}}},"13":{"x":248.4,"y":217.2,"name":"iron","type":"sprite","r":0,"sx":1,"sy":1,"a":1,"skewX":0,"skewY":0,"0":{"type":"bitmap","libName":"iron_qc.png","x":0,"y":0,"r":0,"sx":1,"sy":1,"skewX":0,"skewY":0}}},{"type":"sprite","x":0,"y":0,"name":"ee","0":{"type":"bitmap","libName":"酒精灯_qc.png","x":803.4,"y":1260.85,"r":0,"sx":1,"sy":1,"skewX":0,"skewY":0},"1":{"type":"bitmap","libName":"spirit_lamp.png","x":792.35,"y":1085.35,"r":0,"sx":1,"sy":1,"skewX":0,"skewY":0},"2":{"type":"bitmap","libName":"装有铁丝的支架_qc.png","x":283.95,"y":890.3,"r":0,"sx":1,"sy":1,"skewX":0,"skewY":0},"3":{"type":"bitmap","libName":"火柴盒_qc.png","x":264.95,"y":1260.85,"r":0,"sx":1,"sy":1,"skewX":0,"skewY":0},"4":{"type":"bitmap","libName":"match_box_qc.png","x":264.95,"y":1132.35,"r":0,"sx":1,"sy":1,"skewX":0,"skewY":0},"5":{"type":"bitmap","libName":"iron_qc.png","x":190.45,"y":172.45,"r":0,"sx":1,"sy":1,"skewX":0,"skewY":0}},{"name":"ei","x":0,"y":0,"type":"sprite"},{"name":"cc","x":0,"y":0,"type":"sprite"}]